zhisquant/__init__.py
zhisquant/client.py
zhisquant/exceptions.py
zhisquant/utils.py
zhisquant-0.1.1.dist-info/METADATA
zhisquant-0.1.1.dist-info/WHEEL
zhisquant-0.1.1.dist-info/top_level.txt
zhisquant-0.1.1.dist-info/RECORD
