Metadata-Version: 2.1
Name: zhisquant
Version: 0.1.1
Summary: ZhiSQuant SDK for interacting with the ZhiSQuant API
Home-page: UNKNOWN
Author: Maple
Author-email: mapleccs@outlook.com
License: UNKNOWN
Platform: UNKNOWN
Classifier: Programming Language :: Python :: 3
Classifier: License :: OSI Approved :: MIT License
Classifier: Operating System :: OS Independent
Requires-Python: >=3.6
Requires-Dist: requests >=2.0.0
Requires-Dist: pandas >=1.0.0
